acme/__init__.py
acme/core.py
acme/version.py
python_package_experiment_acme-0.1.0.dist-info/LICENSE.txt
python_package_experiment_acme-0.1.0.dist-info/METADATA
python_package_experiment_acme-0.1.0.dist-info/WHEEL
python_package_experiment_acme-0.1.0.dist-info/entry_points.txt
python_package_experiment_acme-0.1.0.dist-info/top_level.txt
python_package_experiment_acme-0.1.0.dist-info/RECORD
