Metadata-Version: 2.1
Name: python-package-experiment-acme
Version: 0.1.0
Summary: ika
Home-page: https://www.example.com/
Author: Norio Kimura
Author-email: kimura@example.com
License: MIT
Platform: UNKNOWN
Requires-Dist: six
Provides-Extra: dev
Requires-Dist: pytest; extra == 'dev'
Requires-Dist: tox; extra == 'dev'
